headerparser/__init__.py
headerparser/errors.py
headerparser/normdict.py
headerparser/parser.py
headerparser/py.typed
headerparser/scanner.py
headerparser/types.py
headerparser/util.py
headerparser-0.5.2.dist-info/METADATA
headerparser-0.5.2.dist-info/WHEEL
headerparser-0.5.2.dist-info/licenses/LICENSE
headerparser-0.5.2.dist-info/RECORD
