Metadata-Version: 2.3
Name: headerparser
Version: 0.5.2
Summary: argparse for mail-style headers
Project-URL: Source Code, https://github.com/wheelodex/headerparser
Project-URL: Bug Tracker, https://github.com/wheelodex/headerparser/issues
Project-URL: Documentation, https://headerparser.readthedocs.io
Author-email: John Thorvald Wodder II <headerparser@varonathe.org>
License: MIT
Keywords: e-mail,email,headers,mail,parser,rfc2822,rfc5322,rfc822
Classifier: Intended Audience :: Developers
Classifier: License :: OSI Approved :: MIT License
Classifier: Programming Language :: Python :: 3
Classifier: Programming Language :: Python :: 3 :: Only
Classifier: Programming Language :: Python :: 3.8
Classifier: Programming Language :: Python :: 3.9
Classifier: Programming Language :: Python :: 3.10
Classifier: Programming Language :: Python :: 3.11
Classifier: Programming Language :: Python :: 3.12
Classifier: Programming Language :: Python :: 3.13
Classifier: Programming Language :: Python :: Implementation :: CPython
Classifier: Programming Language :: Python :: Implementation :: PyPy
Classifier: Topic :: Communications :: Email
Classifier: Topic :: Communications :: Usenet News
Classifier: Topic :: Internet :: WWW/HTTP
Classifier: Topic :: Text Processing
Classifier: Typing :: Typed
Requires-Python: >=3.8
Requires-Dist: attrs>=20.1.0
Requires-Dist: deprecated~=1.2
